setup.py
pidantic/__init__.py
pidantic/pidantic_exceptions.py
pidantic/pidbase.py
pidantic/state_machine.py
pidantic/ui.py
pidantic.egg-info/PKG-INFO
pidantic.egg-info/SOURCES.txt
pidantic.egg-info/dependency_links.txt
pidantic.egg-info/requires.txt
pidantic.egg-info/top_level.txt
pidantic/fork/__init__.py
pidantic/fork/pidfork.py
pidantic/pyon/__init__.py
pidantic/pyon/persistence.py
pidantic/pyon/pidpyon.py
pidantic/pyon/pyon.py
pidantic/supd/__init__.py
pidantic/supd/persistence.py
pidantic/supd/pidsupd.py
pidantic/supd/supd.py