Metadata-Version: 1.0
Name: pidantic
Version: 0.1.2
Summary: An abstraction to process management for OOI
Home-page: https://github.com/nimbusproject/pidantic
Author: Nimbus Development Team
Author-email: workspace-user@globus.org
License: Apache2
Download-URL: http://www.nimbusproject.org/downloads/pidantic-0.1.2.tar.gz
Keywords: OOI PID process fork supervisord ION
Platform: UNKNOWN
Classifier: Development Status :: 4 - Beta
Classifier: Environment :: Console
Classifier: Intended Audience :: End Users/Desktop
Classifier: Intended Audience :: Developers
Classifier: Intended Audience :: System Administrators
Classifier: License :: OSI Approved :: Apache Software License
Classifier: Operating System :: MacOS :: MacOS X
Classifier: Operating System :: Microsoft :: Windows
Classifier: Operating System :: POSIX
Classifier: Operating System :: POSIX :: Linux
Classifier: Programming Language :: Python
Classifier: Topic :: System :: Clustering
Classifier: Topic :: System :: Distributed Computing
